Metadata-Version: 2.1
Name: django-soap
Version: 0.1.4
Summary: Your project description goes here
Home-page: https://github.com/Lenders-Cooperative/Django-SOAP
Author: Stephen Lightcap
Author-email: you@example.com
License: BSD
Keywords: django-soap
Platform: UNKNOWN
Classifier: Development Status :: 3 - Alpha
Classifier: Framework :: Django
Classifier: Intended Audience :: Developers
Classifier: License :: OSI Approved :: BSD License
Classifier: Natural Language :: English
Classifier: Programming Language :: Python :: 3
Classifier: Programming Language :: Python :: 3.5
Classifier: Programming Language :: Python :: 3.6
License-File: LICENSE
License-File: AUTHORS.rst
